setup.py
rotatedicom/Rotateimage.py
rotatedicom/__init__.py
rotatedicom.egg-info/PKG-INFO
rotatedicom.egg-info/SOURCES.txt
rotatedicom.egg-info/dependency_links.txt
rotatedicom.egg-info/top_level.txt